combot/__init__.py
combot/placeholder.py
combot-0.0.2.dist-info/LICENSE
combot-0.0.2.dist-info/METADATA
combot-0.0.2.dist-info/WHEEL
combot-0.0.2.dist-info/top_level.txt
combot-0.0.2.dist-info/RECORD
