Metadata-Version: 2.1
Name: combot
Version: 0.0.2
Summary: combot
Home-page: https://github.com/combot-tools/combot-py
Author: xxninjabunnyxx
Author-email: xxninjabunnyxx@gmail.com
License: UNKNOWN
Project-URL: Bug Tracker, https://github.com/combot-tools/combot-py/issues
Platform: UNKNOWN
Classifier: Programming Language :: Python :: 3
Classifier: License :: OSI Approved :: MIT License
Classifier: Operating System :: OS Independent
Requires-Python: >=3.6
License-File: LICENSE
